src/__init__.py
src/__main__.py
src/tests/__init__.py
src/tests/test_access_token.py
src/tests/test_generic_controller.py
src/tests/test_main.py
DataExtractionPackage-1.1.0.dist-info/LICENSE
DataExtractionPackage-1.1.0.dist-info/METADATA
DataExtractionPackage-1.1.0.dist-info/WHEEL
DataExtractionPackage-1.1.0.dist-info/top_level.txt
DataExtractionPackage-1.1.0.dist-info/RECORD
