Metadata-Version: 2.1
Name: DataExtractionPackage
Version: 1.1.0
Summary: A package to extract data from Collibra
Home-page: https://github.com/cjlynch278/DSDataExtraction
Author: Chris_Lynch
Author-email: c.lynch278@gmail.com
License: UNKNOWN
Platform: UNKNOWN
Classifier: Programming Language :: Python :: 3
Classifier: License :: OSI Approved :: MIT License
Classifier: Operating System :: OS Independent
License-File: LICENSE
